base-containers/context.yml
base-containers/base/Dockerfile
base-containers/base/README.md
base-containers/base/bin/INGInious
base-containers/base/bin/_run_student_intern
base-containers/base/bin/archive
base-containers/base/bin/feedback
base-containers/base/bin/feedback-custom
base-containers/base/bin/feedback-grade
base-containers/base/bin/feedback-msg
base-containers/base/bin/feedback-msg-tpl
base-containers/base/bin/feedback-result
base-containers/base/bin/feedback-state
base-containers/base/bin/getinput
base-containers/base/bin/inginious-ipython
base-containers/base/bin/parsetemplate
base-containers/base/bin/rst-code
base-containers/base/bin/rst-image
base-containers/base/bin/rst-indent
base-containers/base/bin/rst-msgblock
base-containers/base/bin/run_student
base-containers/base/bin/ssh_student
base-containers/base/bin/tag
base-containers/base/bin/tag-set
base-containers/base/inginious_container_api/__init__.py
base-containers/base/inginious_container_api/feedback.py
base-containers/base/inginious_container_api/input.py
base-containers/base/inginious_container_api/lang.py
base-containers/base/inginious_container_api/rst.py
base-containers/base/inginious_container_api/run_student.py
base-containers/base/inginious_container_api/run_types.py
base-containers/base/inginious_container_api/ssh_student.py
base-containers/base/inginious_container_api/utils.py
base-containers/default/Dockerfile
base-containers/default/README.md
deploy/agent-docker.containerfile
deploy/agent-mcq.containerfile
deploy/backend.containerfile
deploy/context.yml
deploy/db_setup.py
deploy/frontend.containerfile
deploy/inginious-base.containerfile
doc/Makefile
doc/admin_documentation.rst
doc/conf.py
doc/developer_documentation.rst
doc/index.rst
doc/logo_rtd.svg
doc/make.bat
doc/teacher_documentation.rst
doc/what_is_inginious.rst
doc/admin_doc/commands_doc/inginious-agent-docker.rst
doc/admin_doc/commands_doc/inginious-agent-mcq.rst
doc/admin_doc/commands_doc/inginious-autotest.rst
INGInious-0.9.1.dist-info/LICENSE
INGInious-0.9.1.dist-info/METADATA
INGInious-0.9.1.dist-info/WHEEL
INGInious-0.9.1.dist-info/entry_points.txt
INGInious-0.9.1.dist-info/top_level.txt
INGInious-0.9.1.dist-info/RECORD
