Metadata-Version: 2.1
Name: INGInious
Version: 0.9.1
Summary: An intelligent grader that allows secured and automated testing of code made by students.
Author-email: INGInious contributors <inginious@info.ucl.ac.be>
License: AGPL 3
Project-URL: Homepage, https://inginious.org/
Project-URL: Documentation, https://docs.inginious.org
Project-URL: Repository, https://github.com/INGInious/INGInious
Project-URL: Issues, https://github.com/INGInious/INGInious/issues
Keywords: autograder,programming,training,learning,education,mooc,autograding,evaluation,grading,exercise,interview,assessment,lti,learn-to-code,programming-exercise,e-assessment,technical-coding-interview,coding-interviews,inginious
Classifier: Programming Language :: Python :: 3
Classifier: Programming Language :: JavaScript
Classifier: Framework :: Flask
Classifier: Framework :: Pytest
Classifier: Framework :: Setuptools Plugin
Classifier: Framework :: Sphinx
Classifier: Framework :: AsyncIO
Classifier: Intended Audience :: Education
Classifier: License :: OSI Approved :: GNU Affero General Public License v3
Classifier: Topic :: Education
Classifier: Topic :: Education :: Computer Aided Instruction (CAI)
Classifier: Topic :: Scientific/Engineering
Classifier: Topic :: Software Development
Classifier: Operating System :: POSIX :: Linux
Requires-Python: >=3.9
License-File: LICENSE
Requires-Dist: docker==7.1.0
Requires-Dist: docutils==0.21.2
Requires-Dist: Flask==3.0.2
Requires-Dist: Flask-Mail==0.10.0
Requires-Dist: itsdangerous==2.2.0
Requires-Dist: Jinja2==3.1.5
Requires-Dist: lti==0.9.5
Requires-Dist: PyLTI1p3==2.0.0
Requires-Dist: MarkupSafe==3.0.2
Requires-Dist: msgpack==1.1.0
Requires-Dist: natsort==8.4.0
Requires-Dist: psutil==6.1.1
Requires-Dist: pymongo==4.11
Requires-Dist: pytidylib==0.3.2
Requires-Dist: PyYAML==6.0.2
Requires-Dist: pyzmq==26.2.1
Requires-Dist: requests==2.31.0
Requires-Dist: requests-oauthlib==2.0.0
Requires-Dist: sh==2.2.1
Requires-Dist: watchdog==6.0.0
Requires-Dist: Werkzeug==3.0.1
Requires-Dist: WsgiDAV==4.3.3
Requires-Dist: zipstream==1.1.4
Requires-Dist: argon2-cffi==23.1.0
Provides-Extra: doc
Requires-Dist: ipython==8.12.3; extra == "doc"
Requires-Dist: sphinx==7.4.7; extra == "doc"
Requires-Dist: sphinx-autodoc-typehints==2.3.0; extra == "doc"
Requires-Dist: sphinx-rtd-theme==3.0.0; extra == "doc"
Requires-Dist: sphinx-tabs==3.4.5; extra == "doc"
Provides-Extra: ldap
Requires-Dist: ldap3==2.9.1; extra == "ldap"
Provides-Extra: saml2
Requires-Dist: python3-saml==1.16.0; extra == "saml2"
Provides-Extra: test
Requires-Dist: pytest==8.3.4; extra == "test"
Requires-Dist: coverage==7.6.9; extra == "test"
